ddgimage/__init__.py
ddgimage/client.py
ddgimage/exceptions.py
ddgimage/models.py
ddgimage-0.1.0.dist-info/METADATA
ddgimage-0.1.0.dist-info/WHEEL
ddgimage-0.1.0.dist-info/licenses/LICENSE
ddgimage-0.1.0.dist-info/RECORD
