Metadata-Version: 2.4
Name: ddgimage
Version: 0.1.0
Summary: A modern, async Python library for DuckDuckGo image searching and crawling.
Author-email: Ajay Sharma <xelionaj@gmail.com>
License-Expression: MIT
License-File: LICENSE
Requires-Python: >=3.12
Requires-Dist: aiofiles>=24.1.0
Requires-Dist: beautifulsoup4>=4.13.4
Requires-Dist: httpx[http2]>=0.28.1
Requires-Dist: lxml>=6.0.0
Requires-Dist: pydantic>=2.11.7
Provides-Extra: dev
Requires-Dist: pytest; extra == 'dev'
Requires-Dist: pytest-asyncio; extra == 'dev'
Requires-Dist: pytest-mock; extra == 'dev'
Requires-Dist: ruff; extra == 'dev'
